LICENSE
MANIFEST.in
README.rst
setup.py
src/sentry_statsd/__init__.py
src/sentry_statsd/forms.py
src/sentry_statsd/plugin.py
src/sentry_statsd.egg-info/PKG-INFO
src/sentry_statsd.egg-info/SOURCES.txt
src/sentry_statsd.egg-info/dependency_links.txt
src/sentry_statsd.egg-info/entry_points.txt
src/sentry_statsd.egg-info/not-zip-safe
src/sentry_statsd.egg-info/requires.txt
src/sentry_statsd.egg-info/top_level.txt