Metadata-Version: 1.0
Name: sentry-statsd
Version: 0.0.2
Summary: A Sentry extension which send errors stats to StatsD
Home-page: http://github.com/dreadatour/sentry-statsd
Author: Vladimir Rudnyh
Author-email: dreadatour@gmail.com
License: WTFPL
Keywords: sentry statsd
Platform: UNKNOWN
Classifier: Intended Audience :: Developers
Classifier: Intended Audience :: System Administrators
Classifier: Operating System :: OS Independent
Classifier: Programming Language :: Python
Classifier: Framework :: Django
Classifier: Topic :: Software Development
